addseconds/__init__.py
addseconds/templatetags/__init__.py
addseconds/templatetags/addseconds.py
django_addseconds-0.0.2b1.dist-info/LICENSE
django_addseconds-0.0.2b1.dist-info/METADATA
django_addseconds-0.0.2b1.dist-info/WHEEL
django_addseconds-0.0.2b1.dist-info/top_level.txt
django_addseconds-0.0.2b1.dist-info/RECORD
